{
    "algorithms": [],
    "args": [
        "jsonschema",
        "py7zr>=0.20.2",
        "simplejson",
        "tqdm",
        "typing-extensions"
    ],
    "aria": [
        "aria2p",
        "requests"
    ],
    "asynchronous": [],
    "atomic": [
        "py7zr>=0.20.2",
        "tqdm"
    ],
    "av": [
        "av>=8.0; python_version>='3.8'",
        "numpy"
    ],
    "bench": [],
    "benchmarks": [
        "numba; python_version<'3.11'",
        "numpy"
    ],
    "binary": [],
    "browscap": [
        "re2"
    ],
    "bs4": [
        "beautifulsoup4"
    ],
    "cache": [
        "jsonschema",
        "msgpack>=0.6.0",
        "py7zr>=0.20.2",
        "simplejson",
        "tqdm",
        "typing-extensions"
    ],
    "casedict": [],
    "cholesky": [
        "numba; python_version<'3.11'",
        "numpy"
    ],
    "compat": [
        "gmpy2"
    ],
    "concurrency": [],
    "config": [
        "jsonschema",
        "py7zr>=0.20.2",
        "simplejson",
        "sortedcontainers",
        "toml",
        "tqdm",
        "typing-extensions"
    ],
    "constants_physics": [],
    "constants_video": [],
    "cpython": [],
    "crypto": [],
    "csv": [],
    "cv": [
        "numpy",
        "opencv-python",
        "wxPython>=4"
    ],
    "datastructures": [],
    "datetime": [],
    "dbm": [],
    "debug": [],
    "dict": [],
    "downloadmanager": [
        "aiohttp>=3.7.4",
        "wxasync",
        "wxPython>=4"
    ],
    "encoder": [
        "nltk>=3.6.1",
        "numpy"
    ],
    "error": [],
    "exceptions": [],
    "factorial": [],
    "file": [
        "py7zr>=0.20.2",
        "tqdm"
    ],
    "fileformats": [
        "jsonschema",
        "pandas",
        "piexif",
        "py7zr>=0.20.2",
        "setuptools",
        "simplejson",
        "tqdm",
        "typing-extensions"
    ],
    "filesdb": [
        "py7zr>=0.20.2",
        "tls-property>=1.0.1",
        "tqdm"
    ],
    "filesystem": [
        "py7zr>=0.20.2",
        "tqdm"
    ],
    "fingerprinting": [
        "numpy",
        "Pillow>=8.1.1"
    ],
    "flask": [
        "flask>=0.12.3",
        "werkzeug>=0.11.11"
    ],
    "func": [],
    "gensim": [
        "gensim>=4.0.0",
        "keras",
        "numpy",
        "py7zr>=0.20.2",
        "tqdm"
    ],
    "geometry": [],
    "graph": [],
    "hardware": [
        "ctypes-windows-sdk>=0.0.10; sys_platform=='win32'"
    ],
    "hash": [
        "py7zr>=0.20.2",
        "tqdm"
    ],
    "html": [
        "beautifulsoup4"
    ],
    "http": [
        "certifi",
        "jsonschema",
        "py7zr>=0.20.2",
        "requests",
        "simplejson",
        "tqdm",
        "typing-extensions"
    ],
    "image": [
        "numpy"
    ],
    "imdb": [],
    "implementationdetail": [],
    "indexing": [],
    "iter": [],
    "json": [
        "jsonschema",
        "py7zr>=0.20.2",
        "simplejson",
        "tqdm",
        "typing-extensions"
    ],
    "latex": [],
    "lda": [
        "jsonschema",
        "nltk>=3.6.1",
        "numpy",
        "py7zr>=0.20.2",
        "scikit-learn",
        "simplejson",
        "tqdm",
        "typing-extensions"
    ],
    "locale": [],
    "logging": [],
    "markdown": [],
    "math": [
        "gmpy2"
    ],
    "mediainfo": [
        "pymediainfo"
    ],
    "metrics": [
        "numpy"
    ],
    "metrictree": [],
    "mongo": [
        "pymongo"
    ],
    "msgpack": [
        "msgpack>=0.6.0",
        "py7zr>=0.20.2",
        "tqdm"
    ],
    "multihash": [
        "py7zr>=0.20.2",
        "rhash; sys_platform=='win32'",
        "tqdm"
    ],
    "net": [
        "netifaces"
    ],
    "networkx": [
        "networkx",
        "numpy"
    ],
    "nlp": [
        "gensim>=4.0.0",
        "keras",
        "nltk>=3.6.1",
        "numpy",
        "py7zr>=0.20.2",
        "tqdm"
    ],
    "nltk": [
        "nltk>=3.6.1"
    ],
    "numba": [
        "numba; python_version<'3.11'"
    ],
    "numpy": [
        "numpy"
    ],
    "object": [
        "jsonschema",
        "py7zr>=0.20.2",
        "simplejson",
        "tqdm",
        "typing-extensions"
    ],
    "ops": [],
    "os": [
        "ctypes-windows-sdk>=0.0.10; sys_platform=='win32'"
    ],
    "os_mac": [],
    "os_posix": [],
    "os_shared": [],
    "os_win": [
        "ctypes-windows-sdk>=0.0.10; sys_platform=='win32'"
    ],
    "pandas": [
        "pandas"
    ],
    "parquet": [
        "pyarrow"
    ],
    "pdf": [
        "jsonschema",
        "pdfminer",
        "py7zr>=0.20.2",
        "PyPDF2>=3.0.0",
        "simplejson",
        "tika",
        "tqdm",
        "typing-extensions"
    ],
    "pickle": [
        "py7zr>=0.20.2",
        "tqdm"
    ],
    "pillow": [
        "piexif",
        "Pillow>=8.1.1"
    ],
    "powerpoint": [
        "python-pptx"
    ],
    "profile": [],
    "rand": [],
    "rasa": [
        "aiohttp>=3.7.4",
        "requests",
        "ruamel.yaml"
    ],
    "regression": [
        "numpy"
    ],
    "resizing": [
        "numpy",
        "opencv-python",
        "scikit-learn"
    ],
    "rich": [
        "rich"
    ],
    "ringlist": [],
    "salesforce": [
        "aiohttp>=3.7.4",
        "jsonschema",
        "pandas",
        "py7zr>=0.20.2",
        "requests",
        "simple-salesforce>=1.1.0",
        "simplejson",
        "tqdm",
        "typing-extensions"
    ],
    "scene_change_detection": [
        "numpy",
        "opencv-python",
        "wxPython>=4"
    ],
    "scipy": [
        "numpy",
        "scipy"
    ],
    "scrapy": [
        "brotli"
    ],
    "search": [],
    "segment_tree": [],
    "sequence": [],
    "set": [],
    "signal": [],
    "sort": [
        "py7zr>=0.20.2",
        "tqdm"
    ],
    "spark": [
        "pyspark>=3.0.0"
    ],
    "sparql": [
        "pandas",
        "requests"
    ],
    "sql": [
        "py7zr>=0.20.2",
        "tqdm"
    ],
    "sqlite": [],
    "statistics": [
        "gmpy2"
    ],
    "stdio": [],
    "string": [],
    "sudoku": [
        "gmpy2"
    ],
    "sys": [],
    "tensorflow": [
        "tensorflow"
    ],
    "test": [
        "py7zr>=0.20.2",
        "tqdm"
    ],
    "tests": [
        "aiohttp>=3.7.4",
        "aioresponses>=0.7.2",
        "av>=8.0; python_version>='3.8'",
        "ctypes-windows-sdk>=0.0.10; sys_platform=='win32'",
        "flask>=0.12.3",
        "gensim>=4.0.0",
        "gmpy2",
        "hypothesis",
        "jsonschema",
        "keras",
        "msgpack>=0.6.0",
        "nltk>=3.6.1",
        "numba; python_version<'3.11'",
        "numpy",
        "opencv-python",
        "packaging",
        "pandas",
        "pdfminer",
        "Pillow>=8.1.1",
        "py7zr>=0.20.2",
        "PyPDF2>=3.0.0",
        "pywin32; sys_platform=='win32'",
        "requests",
        "requests-mock",
        "ruamel.yaml",
        "setuptools",
        "simple-salesforce>=1.1.0",
        "simplejson",
        "tika",
        "tls-property>=1.0.1",
        "toml",
        "tqdm",
        "typing-extensions",
        "werkzeug>=0.11.11"
    ],
    "text": [
        "jsonschema",
        "msgpack>=0.6.0",
        "py7zr>=0.20.2",
        "simplejson",
        "tqdm",
        "typing-extensions"
    ],
    "text_segmentation": [],
    "text_summarization": [
        "numpy",
        "py7zr>=0.20.2",
        "spacy",
        "tqdm"
    ],
    "time": [],
    "tls": [
        "cryptography>=1.5.3",
        "pyOpenSSL>=17.5.0"
    ],
    "toml": [
        "toml"
    ],
    "torch": [
        "torch"
    ],
    "torrent": [
        "bencode.py>=2.0.0",
        "jsonschema",
        "py7zr>=0.20.2",
        "requests",
        "simplejson",
        "tqdm",
        "typing-extensions"
    ],
    "tree": [],
    "twisted": [
        "twisted"
    ],
    "twitch": [
        "certifi",
        "jsonschema",
        "py7zr>=0.20.2",
        "requests",
        "simplejson",
        "tqdm",
        "typing-extensions"
    ],
    "typing": [
        "typing-extensions"
    ],
    "unicode": [
        "jsonschema",
        "msgpack>=0.6.0",
        "py7zr>=0.20.2",
        "simplejson",
        "tqdm",
        "typing-extensions"
    ],
    "unqlite": [],
    "url": [],
    "videofile": [
        "av>=8.0; python_version>='3.8'",
        "numpy",
        "opencv-python"
    ],
    "widgets": [
        "wxPython>=4"
    ],
    "win": [
        "ctypes-windows-sdk>=0.0.10; sys_platform=='win32'",
        "pywin32; sys_platform=='win32'"
    ],
    "win32": [
        "pywin32; sys_platform=='win32'",
        "wmi; sys_platform=='win32'"
    ],
    "wsgi": [
        "werkzeug>=0.11.11"
    ],
    "xsl": [
        "lxml"
    ],
    "yaml": [
        "ruamel.yaml"
    ]
}
